dhenara/agent/__init__.py
dhenara/agent/client/__init__.py
dhenara/agent/client/_base.py
dhenara/agent/client/_client.py
dhenara/agent/client/_stream.py
dhenara/agent/client/_urls.py
dhenara/agent/client/types/fns/__init__.py
dhenara/agent/client/types/fns/pydantic_endpoint.py
dhenara/agent/client/types/functional_types/__init__.py
dhenara/agent/client/types/functional_types/dhenara/__init__.py
dhenara/agent/client/types/functional_types/dhenara/_api_response/_devtime/_run_endpoint.py
dhenara/agent/client/types/functional_types/dhenara/_api_response/_runtime/_run_endpoint.py
dhenara/agent/config/__init__.py
dhenara/agent/config/_config.py
dhenara/agent/dsl/__init__.py
dhenara/agent/dsl/base/__init__.py
dhenara/agent/dsl/base/context.py
dhenara/agent/dsl/base/context_registry.py
dhenara/agent/dsl/base/defs.py
dhenara/agent/dsl/base/enums.py
dhenara/agent/dsl/base/executable.py
dhenara/agent/dsl/base/fns.py
dhenara/agent/dsl/base/callback/callback.py
dhenara/agent/dsl/base/callback/callback_io.py
dhenara/agent/dsl/base/component/_component_registry.py
dhenara/agent/dsl/base/component/comp_exe_result.py
dhenara/agent/dsl/base/component/component.py
dhenara/agent/dsl/base/component/component_def.py
dhenara/agent/dsl/base/component/component_io.py
dhenara/agent/dsl/base/component/control.py
dhenara/agent/dsl/base/component/executor.py
dhenara/agent/dsl/base/data/dad_template_engine.py
dhenara/agent/dsl/base/data/template_engine.py
dhenara/agent/dsl/base/node/_executor_registry.py
dhenara/agent/dsl/base/node/node.py
dhenara/agent/dsl/base/node/node_def.py
dhenara/agent/dsl/base/node/node_exe_result.py
dhenara/agent/dsl/base/node/node_executor.py
dhenara/agent/dsl/base/node/node_io.py
dhenara/agent/dsl/base/node/node_settings.py
dhenara/agent/dsl/base/utils/__init__.py
dhenara/agent/dsl/base/utils/id_mixin.py
dhenara/agent/dsl/components/agent/__init__.py
dhenara/agent/dsl/components/agent/component.py
dhenara/agent/dsl/components/flow/__init__.py
dhenara_agent-0.3.3.dist-info/METADATA
dhenara_agent-0.3.3.dist-info/WHEEL
dhenara_agent-0.3.3.dist-info/entry_points.txt
dhenara_agent-0.3.3.dist-info/RECORD
