Metadata-Version: 2.4
Name: dhenara-agent
Version: 0.3.3
Summary: Dhenara Agent DSL (DAD) Framework SDK
Project-URL: Homepage, https://dhenara.com
Project-URL: Documentation, https://docs.dhenara.com/
Project-URL: Bug Reports, https://github.com/dhenara/dhenara-agent/issues
Project-URL: Source Code, https://github.com/dhenara/dhenara-agent
Author-email: Dhenara Inc <support@dhenara.com>
License-Expression: MIT
Keywords: agent,ai,framework,llm
Classifier: Development Status :: 3 - Alpha
Classifier: Intended Audience :: Developers
Classifier: License :: OSI Approved :: MIT License
Classifier: Operating System :: OS Independent
Classifier: Programming Language :: Python :: 3
Classifier: Programming Language :: Python :: 3.13
Classifier: Topic :: Scientific/Engineering :: Artificial Intelligence
Requires-Python: <3.14,>=3.13
Requires-Dist: click>=8.0.0
Requires-Dist: dhenara-ai>=1.1.1
Requires-Dist: httpx>=0.24.0
Requires-Dist: opentelemetry-api>=1.20.0
Requires-Dist: opentelemetry-exporter-otlp>=1.20.0
Requires-Dist: opentelemetry-exporter-zipkin
Requires-Dist: opentelemetry-instrumentation>=0.40b0
Requires-Dist: opentelemetry-sdk>=1.20.0
Requires-Dist: pydantic>=2.0.0
Requires-Dist: pyyaml>=6.0
Requires-Dist: requests>=2.25.1
Provides-Extra: dev
Requires-Dist: pytest-asyncio>=0.18.0; extra == 'dev'
Requires-Dist: pytest-cov>=3.0.0; extra == 'dev'
Requires-Dist: pytest>=7.0.0; extra == 'dev'
Provides-Extra: observability
Requires-Dist: opentelemetry-exporter-jaeger>=1.20.0; extra == 'observability'
